{
  "project_info": {
    "project_number": "927391060869",
    "project_id": "vendorconnect-b58dc",
    "storage_bucket": "vendorconnect-b58dc.firebasestorage.app"
  },
  "client": [
    {
      "client_info": {
        "mobilesdk_app_id": "1:927391060869:android:84c280d0a9ed2b5f2aaaec",
        "android_client_info": {
          "package_name": "com.example.vendorconnect"
        }
      },
      "oauth_client": [],
      "api_key": [
        {
          "current_key": "AIzaSyCfggNMqkZoDz2tVIsBQLYwPzJs0eaKyl8"
        }
      ],
      "services": {
        "appinvite_service": {
          "other_platform_oauth_client": []
        }
      }
    }
  ],
  "configuration_version": "1"
}